chemtools/__init__.py
chemtools/basisopt.py
chemtools/basisparse.py
chemtools/basisset.py
chemtools/cbs.py
chemtools/cli.py
chemtools/integrals.py
chemtools/molecule.py
chemtools/parsetools.py
chemtools/submitgamess.py
chemtools/submitmolpro.py
chemtools/calculators/__init__.py
chemtools/calculators/calculator.py
chemtools/calculators/dalton.py
chemtools/calculators/dmft.py
chemtools/calculators/gamessorbitals.py
chemtools/calculators/gamessreader.py
chemtools/calculators/gamessus.py
chemtools/calculators/molpro.py
chemtools/calculators/psi4.py
chemtools/pescan/__init__.py
chemtools/pescan/controller.py
chemtools/pescan/model.py
chemtools-0.9.2.data/scripts/submitgamess.py
chemtools-0.9.2.data/scripts/submitmolpro.py
chemtools-0.9.2.dist-info/LICENSE.rst
chemtools-0.9.2.dist-info/METADATA
chemtools-0.9.2.dist-info/WHEEL
chemtools-0.9.2.dist-info/entry_points.txt
chemtools-0.9.2.dist-info/top_level.txt
chemtools-0.9.2.dist-info/RECORD
