Metadata-Version: 2.1
Name: chemtools
Version: 0.9.2
Summary: Python tools for quantum chemical calculations
Home-page: https://github.com/lmmentel/chemtools/
Author: Lukasz Mentel
Author-email: lmmentel@gmail.com
License: MIT
Keywords: basis set,optimization,quantum chemistry,molecular physics
Platform: UNKNOWN
Classifier: Development Status :: 5 - Production/Stable
Classifier: Environment :: Console
Classifier: Intended Audience :: Science/Research
Classifier: License :: OSI Approved :: MIT License
Classifier: Operating System :: OS Independent
Classifier: Programming Language :: Python :: 3
Classifier: Topic :: Scientific/Engineering :: Chemistry
Classifier: Topic :: Scientific/Engineering :: Physics
Requires-Dist: sqlalchemy
Requires-Dist: scipy (>=0.11)
Requires-Dist: numpy (>=1.7)
Requires-Dist: mendeleev
Requires-Dist: numba
Requires-Dist: pandas
